.bumpversion.cfg
AUTHORS.rst
CHANGELOG.rst
CONTRIBUTING.rst
LICENSE
MANIFEST.in
README.rst
find_gsl.py
link_pyqt.py
setup.cfg
setup.py
tox.ini
docs/.gitignore
docs/Makefile
docs/authors.rst
docs/changelog.rst
docs/conf.py
docs/contributing.rst
docs/index.rst
docs/install.rst
docs/make.bat
docs/overview.rst
docs/quick_start_manual.pdf
docs/quick_start_manual.svg
docs/readme.rst
docs/requirements.txt
docs/virtual_microbes_methods.pdf
docs/reference/VirtualMicrobes.Tree.rst
docs/reference/VirtualMicrobes.cython_gsl_interface.rst
docs/reference/VirtualMicrobes.data_tools.rst
docs/reference/VirtualMicrobes.environment.rst
docs/reference/VirtualMicrobes.event.rst
docs/reference/VirtualMicrobes.mutate.rst
docs/reference/VirtualMicrobes.plotting.rst
docs/reference/VirtualMicrobes.post_analysis.rst
docs/reference/VirtualMicrobes.rst
docs/reference/VirtualMicrobes.simulation.rst
docs/reference/VirtualMicrobes.virtual_cell.rst
docs/reference/glossary.rst
docs/reference/index.rst
src/.gitignore
src/VirtualMicrobes/__init__.py
src/VirtualMicrobes.egg-info/PKG-INFO
src/VirtualMicrobes.egg-info/SOURCES.txt
src/VirtualMicrobes.egg-info/dependency_links.txt
src/VirtualMicrobes.egg-info/requires.txt
src/VirtualMicrobes.egg-info/top_level.txt
src/VirtualMicrobes/Tree/PhyloTree.py
src/VirtualMicrobes/Tree/__init__.py
src/VirtualMicrobes/cython_gsl_interface/.gitignore
src/VirtualMicrobes/cython_gsl_interface/__init__.py
src/VirtualMicrobes/cython_gsl_interface/integrate.c
src/VirtualMicrobes/cython_gsl_interface/integrate.pxd
src/VirtualMicrobes/cython_gsl_interface/integrate.pyx
src/VirtualMicrobes/cython_gsl_interface/odes.c
src/VirtualMicrobes/cython_gsl_interface/odes.h
src/VirtualMicrobes/cython_gsl_interface/odes.pxd
src/VirtualMicrobes/cython_gsl_interface/odes.pyx
src/VirtualMicrobes/data_tools/__init__.py
src/VirtualMicrobes/data_tools/store.py
src/VirtualMicrobes/environment/Environment.py
src/VirtualMicrobes/environment/Grid.py
src/VirtualMicrobes/environment/__init__.py
src/VirtualMicrobes/event/Molecule.py
src/VirtualMicrobes/event/Reaction.py
src/VirtualMicrobes/event/__init__.py
src/VirtualMicrobes/mutate/Mutation.py
src/VirtualMicrobes/mutate/__init__.py
src/virtual_microbes.egg-info/PKG-INFO
src/virtual_microbes.egg-info/SOURCES.txt
src/virtual_microbes.egg-info/dependency_links.txt
src/virtual_microbes.egg-info/requires.txt
src/virtual_microbes.egg-info/top_level.txt
